asset/__init__.py
asset/asset_register.py
asset/asset_table.py
asset/base.py
asset/cli.py
asset/commands.py
asset/conf.py
asset/ctx.py
asset/exceptions.py
asset/schema.py
asset/tools.py
asset/utils.py
asset/aliyun/__init__.py
asset/aliyun/ecs.py
asset/aliyun/ram.py
asset/aws/__init__.py
asset/aws/account.py
asset/aws/cloudwatch.py
asset/aws/ec2.py
asset/aws/elb.py
asset/aws/elb_v2.py
asset/aws/rds.py
asset/aws/s3.py
asset/huawei/__init__.py
asset/huawei/ecs.py
asset/huawei/vpc.py
asset/tencent/__init__.py
asset/tencent/cam.py
asset/tencent/cdb_mysql.py
asset/tencent/clb.py
asset/tencent/cos.py
asset/tencent/cvm.py
asset/tencent/monitor.py
asset/tencent/vpc.py
cloud_asset-0.0.4.9.dist-info/LICENSE
cloud_asset-0.0.4.9.dist-info/METADATA
cloud_asset-0.0.4.9.dist-info/WHEEL
cloud_asset-0.0.4.9.dist-info/entry_points.txt
cloud_asset-0.0.4.9.dist-info/top_level.txt
cloud_asset-0.0.4.9.dist-info/RECORD
