Metadata-Version: 2.1
Name: cloud-asset
Version: 0.0.4.9
Summary: Cloud Asset - Asset For Postgres
Author: Cloud Asset Authors
Author-email: 
License: Apache-2.0
Requires-Python: >=3.7.1,<4.0
License-File: LICENSE
Requires-Dist: tencentcloud-sdk-python (==3.0.898)
Requires-Dist: aliyun-python-sdk-core (==2.13.36)
Requires-Dist: aliyun-python-sdk-ecs (==4.24.26)
Requires-Dist: aliyun-python-sdk-sts (==3.1.0)
Requires-Dist: aliyun-python-sdk-ram (==3.3.0)
Requires-Dist: boto3 (==1.26.29)
Requires-Dist: huaweicloudsdkcore (==3.1.37)
Requires-Dist: huaweicloudsdkecs (==3.1.37)
Requires-Dist: huaweicloudsdkiam (==3.1.37)
Requires-Dist: huaweicloudsdkevs (==3.1.37)
Requires-Dist: huaweicloudsdkeip (==3.1.37)
Requires-Dist: huaweicloudsdknat (==3.1.37)
Requires-Dist: huaweicloudsdkelb (==3.1.37)
Requires-Dist: huaweicloudsdkvpc (==3.1.37)
Requires-Dist: esdk-obs-python (==3.22.2)
Requires-Dist: SQLAlchemy (==1.4.44)
Requires-Dist: psycopg2 (==2.9.5)
Requires-Dist: click (==8.1.3)
Requires-Dist: pydantic (==1.10.2)
Requires-Dist: requests (==2.28.0)
Requires-Dist: pyyaml (==6.0)
Requires-Dist: arrow (==1.2.3)
